display_setter/__init__.py
display_setter/display_c_module.cp37-win32.pyd
display_setter/displayclass.cp37-win32.pyd
display_setter-1.0.3.dist-info/LICENSE.txt
display_setter-1.0.3.dist-info/METADATA
display_setter-1.0.3.dist-info/WHEEL
display_setter-1.0.3.dist-info/top_level.txt
display_setter-1.0.3.dist-info/RECORD
