Metadata-Version: 2.1
Name: display-setter
Version: 1.0.3
Summary: this is a tool to set display
Home-page: https://github.com/pypa/sampleproject
Author: bamboo.pan
Author-email: bamboo.pan@hp.com
License: UNKNOWN
Keywords: display
Platform: UNKNOWN
Classifier: Development Status :: 3 - Alpha
Classifier: Intended Audience :: Developers
Classifier: Topic :: Software Development :: Build Tools
Classifier: License :: OSI Approved :: MIT License
Classifier: Programming Language :: Python :: 3.7
Classifier: Programming Language :: Python :: 3.8
Requires-Python: >=2.7, !=3.0.*, !=3.1.*, !=3.2.*, !=3.3.*, !=3.4.*, <4
